pywebp2-1.0.0.dist-info/METADATA
pywebp2-1.0.0.dist-info/WHEEL
pywebp2-1.0.0.dist-info/entry_points.txt
pywebp2-1.0.0.dist-info/licenses/LICENSE
pywebp2/__main__.py
pywebp2/__version__.py
pywebp2/_arg_parser.py
pywebp2/core.py
pywebp2-1.0.0.dist-info/RECORD
