Metadata-Version: 2.1
Name: pywebp2
Version: 1.0.0
Summary: Python image converter to webp format
Author-Email: Gabriel Nobrega <gabrieltkdnobrega63@gmail.com>
License: MIT License
Project-URL: Repository, https://github.com/biellSilva/python-webp
Requires-Python: >=3.11
Requires-Dist: pillow>=10.3.0
